LICENSE
README.md
django_auto_repr.py
setup.py
/Users/daniel/Projects/django-auto-repr/LICENSE
/Users/daniel/Projects/django-auto-repr/README.md
/Users/daniel/Projects/django-auto-repr/django_auto_repr.py
/Users/daniel/Projects/django-auto-repr/setup.py
django_auto_repr.egg-info/PKG-INFO
django_auto_repr.egg-info/SOURCES.txt
django_auto_repr.egg-info/dependency_links.txt
django_auto_repr.egg-info/requires.txt
django_auto_repr.egg-info/top_level.txt