Metadata-Version: 1.0
Name: django-auto-repr
Version: 1.1
Summary: Give Django models a useful __repr__
Home-page: https://github.com/dan-passaro/django-auto-repr
Author: Dan Passaro
Author-email: danpassaro@gmail.com
License: MIT
Platform: UNKNOWN
